Products.PloneFormGen-1.8.9-py2.7-nspkg.pth
Products/PloneFormGen/Form.gif
Products/PloneFormGen/README_TESTS.txt
Products/PloneFormGen/__init__.py
Products/PloneFormGen/compile-locales.sh
Products/PloneFormGen/config.py
Products/PloneFormGen/configure.zcml
Products/PloneFormGen/dollarReplace.py
Products/PloneFormGen/events.py
Products/PloneFormGen/exportimport.py
Products/PloneFormGen/patches.py
Products/PloneFormGen/product.txt
Products/PloneFormGen/rebuild_i18n.sh
Products/PloneFormGen/setuphandlers.py
Products/PloneFormGen/upgrades.py
Products/PloneFormGen/upgrades.zcml
Products/PloneFormGen/version.txt
Products/PloneFormGen/analytics/__init__.py
Products/PloneFormGen/analytics/configure.zcml
Products/PloneFormGen/analytics/tracking.pt
Products/PloneFormGen/analytics/tracking.py
Products/PloneFormGen/browser/__init__.py
Products/PloneFormGen/browser/captcha.py
Products/PloneFormGen/browser/configure.zcml
Products/PloneFormGen/browser/embedded.py
Products/PloneFormGen/browser/exportimport.py
Products/PloneFormGen/browser/gpg_encrypt.py
Products/PloneFormGen/browser/jsvariables.py
Products/PloneFormGen/browser/quickedit.pt
Products/PloneFormGen/browser/quickedit.py
Products/PloneFormGen/browser/resources/quickedit.js
Products/PloneFormGen/browser/resources/quickedit.less
Products/PloneFormGen/content/__init__.py
Products/PloneFormGen/content/actionAdapter.py
Products/PloneFormGen/content/customScriptAdapter.py
Products/PloneFormGen/content/field_utils.py
Products/PloneFormGen/content/fields.py
Products/PloneFormGen/content/fieldsBase.py
Products/PloneFormGen/content/fieldset.py
Products/PloneFormGen/content/form.py
Products/PloneFormGen/content/formLikertField.py
Products/PloneFormGen/content/formMailerAdapter.py
Products/PloneFormGen/content/likertField.py
Products/PloneFormGen/content/saveDataAdapter.py
Products/PloneFormGen/content/thanksPage.py
Products/PloneFormGen/content/validationMessages.py
Products/PloneFormGen/content/ya_gpg.py
Products.PloneFormGen-1.8.9.dist-info/LICENSE.txt
Products.PloneFormGen-1.8.9.dist-info/METADATA
Products.PloneFormGen-1.8.9.dist-info/WHEEL
Products.PloneFormGen-1.8.9.dist-info/entry_points.txt
Products.PloneFormGen-1.8.9.dist-info/namespace_packages.txt
Products.PloneFormGen-1.8.9.dist-info/top_level.txt
Products.PloneFormGen-1.8.9.dist-info/RECORD
