Metadata-Version: 2.1
Name: Products.PloneFormGen
Version: 1.8.9
Summary: A through-the-web form generator for Plone
Home-page: http://plone.org/products/ploneformgen
Author: Steve McMahon
Author-email: steve@dcn.org
License: GPL
Keywords: Plone PloneFormGen
Platform: UNKNOWN
Classifier: Development Status :: 6 - Mature
Classifier: Topic :: Software Development :: Libraries :: Python Modules
Classifier: Framework :: Zope2
Classifier: Framework :: Plone
Classifier: Framework :: Plone :: 5.0
Classifier: License :: OSI Approved :: GNU General Public License v2 (GPLv2)
Classifier: Operating System :: OS Independent
Classifier: Programming Language :: JavaScript
Classifier: Programming Language :: Python
Classifier: Programming Language :: Python :: 2.7
Requires-Dist: setuptools
Requires-Dist: Products.Archetypes (>=1.7.14)
Requires-Dist: Products.CMFPlone (>=5.0b2.dev0)
Requires-Dist: Products.TALESField (>=1.1.3)
Requires-Dist: Products.TemplateFields (>=1.2.4)
Requires-Dist: Products.PythonField (>=1.1.3)
Provides-Extra: loadtest
Requires-Dist: collective.funkload ; extra == 'loadtest'
Provides-Extra: test
Requires-Dist: Products.PloneTestCase ; extra == 'test'
Requires-Dist: plone.app.testing ; extra == 'test'
Requires-Dist: plone.testing ; extra == 'test'
Requires-Dist: plone.app.upgrade ; extra == 'test'
